find_work/app/__init__.py
find_work/app/__main__.py
find_work/app/py.typed
find_work/app/config/__init__.py
find_work/app/config/types.py
find_work/app/data/__init__.py
find_work/app/data/default_config.toml
find_work/app/tests/__init__.py
find_work/app/tests/test_config_types.py
find_work/app/tests/data/alias_sample.toml
find_work/app/tests/data/flag_sample.toml
find_work/core/__init__.py
find_work/core/cache.py
find_work/core/constants.py
find_work/core/py.typed
find_work/core/reporters.py
find_work/core/utils.py
find_work/core/cli/__init__.py
find_work/core/cli/messages.py
find_work/core/cli/options.py
find_work/core/cli/plugins.py
find_work/core/cli/widgets.py
find_work/core/tests/__init__.py
find_work/core/tests/test_cache.py
find_work/core/tests/test_cli.py
find_work/core/types/__init__.py
find_work/core/types/breadcrumbs.py
find_work/core/types/results.py
find_work/reporters/__init__.py
find_work/reporters/console.py
find_work/reporters/html.py
find_work/reporters/json.py
find_work/reporters/py.typed
find_work/reporters/xml.py
find_work/reporters/tests/__init__.py
find_work/reporters/tests/test_console.py
find_work/reporters/tests/test_html.py
find_work/reporters/tests/test_json.py
find_work/reporters/tests/test_xml.py
find_work-1.0.0.dist-info/METADATA
find_work-1.0.0.dist-info/WHEEL
find_work-1.0.0.dist-info/entry_points.txt
find_work-1.0.0.dist-info/licenses/LICENSE
find_work-1.0.0.dist-info/RECORD
