Metadata-Version: 2.3
Name: find-work
Version: 1.0.0
Summary: Personal advice utility for Gentoo package maintainers
Project-URL: Home, https://find-work.sysrq.in/
Project-URL: Source, https://git.sysrq.in/find-work
Project-URL: Issues, https://bugs.sysrq.in/enter_bug.cgi?product=Software&component=find-work
Project-URL: Changelog, https://find-work.sysrq.in/release-notes.html
Author-email: Anna <cyber@sysrq.in>
License: WTFPL
Keywords: ebuild,gentoo,maintainer,repository
Classifier: Development Status :: 4 - Beta
Classifier: Environment :: Console
Classifier: Intended Audience :: Developers
Classifier: License :: DFSG approved
Classifier: Operating System :: POSIX
Classifier: Programming Language :: Python :: 3 :: Only
Classifier: Topic :: System :: Software Distribution
Classifier: Topic :: Utilities
Classifier: Typing :: Typed
Requires-Python: >=3.11
Requires-Dist: aiohttp<4,>=3
Requires-Dist: click
Requires-Dist: click-aliases
Requires-Dist: deepmerge
Requires-Dist: platformdirs<5,>=4
Requires-Dist: pluggy<2
Requires-Dist: pydantic<3,>=2
Requires-Dist: requests<3,>=2
Requires-Dist: typing-extensions<5,>=4.3.0
Provides-Extra: docs
Requires-Dist: insipid-sphinx-theme; extra == 'docs'
Requires-Dist: sphinx; extra == 'docs'
Requires-Dist: sphinx-prompt; extra == 'docs'
Provides-Extra: tabulate
Requires-Dist: tabulate; extra == 'tabulate'
Provides-Extra: test
Requires-Dist: pkgcore; extra == 'test'
Requires-Dist: pytest; extra == 'test'
Requires-Dist: pytest-import-check; extra == 'test'
Provides-Extra: xml
Requires-Dist: lxml>=4.5; extra == 'xml'
